README.md
setup.py
ANC08JUNE2020GEOG489L2/__init__.py
ANC08JUNE2020GEOG489L2/core_functions.py
ANC08JUNE2020GEOG489L2/gui_main.py
ANC08JUNE2020GEOG489L2/main.py
ANC08JUNE2020GEOG489L2.egg-info/PKG-INFO
ANC08JUNE2020GEOG489L2.egg-info/SOURCES.txt
ANC08JUNE2020GEOG489L2.egg-info/dependency_links.txt
ANC08JUNE2020GEOG489L2.egg-info/not-zip-safe
ANC08JUNE2020GEOG489L2.egg-info/requires.txt
ANC08JUNE2020GEOG489L2.egg-info/top_level.txt