Metadata-Version: 1.0
Name: ANC08JUNE2020GEOG489L2
Version: 1.0
Summary: ANC08JUNE2020GEOG489L2
Home-page: http://drupal.psu.edu/geog489/
Author: GEOG489
Author-email: GEOG489@psu.edu
License: BSD
Platform: UNKNOWN
